django_ajax_utils/__init__.py
django_ajax_utils/apps.py
django_ajax_utils/forms.py
django_ajax_utils/middleware.py
django_ajax_utils/models.py
django_ajax_utils/multiforms.py
django_ajax_utils/pjax.py
django_ajax_utils/reactor_compiler.py
django_ajax_utils/response.py
django_ajax_utils/settings.py
django_ajax_utils/utility.py
django_ajax_utils/views.py
django_ajax_utils/static/django_ajax_utils/js/ajaxform.js
django_ajax_utils/static/django_ajax_utils/js/el.js
django_ajax_utils/static/django_ajax_utils/js/messages.js
django_ajax_utils/static/django_ajax_utils/js/pjax.js
django_ajax_utils/static/django_ajax_utils/js/polyfill.js
django_ajax_utils/static/django_ajax_utils/js/urls.js
django_ajax_utils/static/django_ajax_utils/js/utils.js
django_ajax_utils/static/django_ajax_utils/js/utils_ajax.js
django_ajax_utils/templates/form_utils/layout/default.html
django_ajax_utils/templates/form_utils/layout/foundation.html
django_ajax_utils/templates/form_utils/row/default.html
django_ajax_utils/templates/form_utils/row/foundation.html
django_ajax_utils/templatetags/__init__.py
django_ajax_utils/templatetags/form_utils.py
django_ajax_utils/templatetags/js_urlpatterns.py
django_ajax_utils/templatetags/pjax_tags.py
mireq_django_ajax_utils-0.0.8.dist-info/licenses/AUTHORS
mireq_django_ajax_utils-0.0.8.dist-info/licenses/LICENSE
mireq_django_ajax_utils-0.0.8.dist-info/METADATA
mireq_django_ajax_utils-0.0.8.dist-info/WHEEL
mireq_django_ajax_utils-0.0.8.dist-info/top_level.txt
mireq_django_ajax_utils-0.0.8.dist-info/RECORD
